aboutconfig/__init__.py
aboutconfig/admin.py
aboutconfig/apps.py
aboutconfig/constants.py
aboutconfig/forms.py
aboutconfig/models.py
aboutconfig/serializers.py
aboutconfig/utils.py
aboutconfig/widgets.py
aboutconfig/management/__init__.py
aboutconfig/management/commands/__init__.py
aboutconfig/management/commands/config_warm_cache.py
aboutconfig/migrations/0001_initial.py
aboutconfig/migrations/0002_initial_data.py
aboutconfig/migrations/__init__.py
aboutconfig/static/aboutconfig/config_admin.js
aboutconfig/templatetags/__init__.py
aboutconfig/templatetags/config.py
django_aboutconfig-1.1.0.dist-info/DESCRIPTION.rst
django_aboutconfig-1.1.0.dist-info/METADATA
django_aboutconfig-1.1.0.dist-info/RECORD
django_aboutconfig-1.1.0.dist-info/WHEEL
django_aboutconfig-1.1.0.dist-info/metadata.json
django_aboutconfig-1.1.0.dist-info/top_level.txt
