Metadata-Version: 2.0
Name: django-aboutconfig
Version: 1.1.0
Summary: A firefox-like about:config implementation for one-off settings in Django apps.
Home-page: https://gitlab.com/impala1/django-aboutconfig
Author: Kirill Stepanov
Author-email: mail@kirillstepanov.me
License: GPLv3+
Download-URL: https://gitlab.com/impala1/django-aboutconfig/-/archive/1.1.0/django-aboutconfig-1.1.0.tar.gz
Keywords: django,library,configuration
Platform: UNKNOWN
Classifier: Development Status :: 5 - Production/Stable
Classifier: Framework :: Django
Classifier: Framework :: Django :: 2.0
Classifier: Framework :: Django :: 2.1
Classifier: Framework :: Django :: 2.2
Classifier: Framework :: Django :: 3.0
Classifier: Intended Audience :: Developers
Classifier: License :: OSI Approved :: GNU General Public License v3 or later (GPLv3+)
Classifier: Operating System :: OS Independent
Classifier: Programming Language :: Python
Classifier: Topic :: Internet :: WWW/HTTP
Classifier: Programming Language :: Python :: 3
Classifier: Programming Language :: Python :: 3.6
Classifier: Programming Language :: Python :: 3.7
Classifier: Programming Language :: Python :: 3.8
Requires-Python: >=3.6
Requires-Dist: Django (>=2.0)
